{
  "required": true,
  "minVersion": "0.8",
  "package": "ca.fxco.moreculling.mixin",
  "compatibilityLevel": "JAVA_21",
  "plugin": "ca.fxco.moreculling.config.MixinConfigPlugin",
  "client": [
    "blockstates.Block_neoforgeDrawSideMixin",
    "models.ItemModelGenerator_cullMixin",
    "models.MultiPartBakedModel_cacheMixin",
    "models.SimpleBakedModel_neoforgeCacheMixin",
    "models.WeightedBakedModel_cacheMixin",
    "models.cullshape.BlockModel_neoforgeCullShapeMixin",
    "renderers.IBakedModelExtension_faceCullingMixin"
  ],
  "injectors": {
    "defaultRequire": 1
  }
}
